[{"__type__":"cc.Prefab","_name":"TracingGraphics","data":{"__id__":1}},{"__type__":"cc.Node","_name":"TracingGraphics","_components":[{"__type__":"cc.Graphics","node":{"__id__":1},"_materials":[{"__uuid__":"6fgBCSDDdPMInvyNlggls2"}],"_lineWidth":55,"_strokeColor":{"__type__":"cc.Color","r":224,"g":28,"b":28},"_lineCap":1,"_fillColor":{"__type__":"cc.Color","r":101,"g":67,"b":33}},{"__type__":"7afd1G+VFxPtJxi3y2EUala","node":{"__id__":1},"strokeColor":{"__type__":"cc.Color","r":101,"g":67,"b":33},"lineWidth":55,"traceAudio":{"__uuid__":"efrehnIdRAuZRwryvIGD+n"},"star":{"__uuid__":"cbfPvPf3pM7pZFpaw+bcsK"},"staringImage":{"__uuid__":"7aC83sViVIOr8eWdAcQurx"},"arrowImage":{"__uuid__":"4eB6E5EoZJD5qF2xdw0mY/"},"endingImage":{"__uuid__":"294r0zUKFEtbsJXlgZR6RM"},"indicator":{"__uuid__":"8dq7sJmrBPVqZ6dIBZGFAu"},"tracingNode":{"__uuid__":"89iPjnjTVH/YB9pLly2jLk"},"arrowNode":{"__uuid__":"a9YkwEgwlJsJ6JAuHDfbRm"},"imageNode":{"__uuid__":"01f3gOl2ZIL5/A6T4MRvZr"},"tracingImageNode":{"__uuid__":"08O87iaFVOwqdn4knjw/Kf"},"indicatorNode":{"__uuid__":"31McsRwsdECKG9lhJD0sDQ"}}],"_prefab":{"__type__":"cc.PrefabInfo","root":{"__id__":1},"asset":{"__uuid__":"8beQfKEnVE/YT+eXO7+b+H"},"fileId":"c2GyeBtOBG3KWZC9gOzhVJ"},"_anchorPoint":{"__type__":"cc.Vec2"},"_trs":{"__type__":"TypedArray","ctor":"Float64Array","array":[0,0,0,0,0,0,1,1,1,1]}}]