[{"__type__":"cc.SpriteFrame","content":{"name":"default_white_panel","texture":"90foRryRJM3p9AGFGyKh5x","rect":[0,0,21,21],"offset":[0,0],"originalSize":[21,21],"capInsets":[3,3,3,3]}},{"__type__":"cc.SpriteFrame","content":{"name":"shapetractor_crops1","texture":"85gFhlbKlHlKT7lDv8zvN8","rect":[0,0,277,71],"offset":[0,0],"originalSize":[277,71],"capInsets":[0,0,0,0]}},{"__type__":"cc.SpriteFrame","content":{"name":"shapetractor_crops2","texture":"33ER745NVCPqPQ4xRuzAJ4","rect":[0,0,130,87],"offset":[0,0],"originalSize":[130,87],"capInsets":[0,0,0,0]}},{"__type__":"cc.SpriteFrame","content":{"name":"shapetractor_cloud","texture":"f2Dk1ztHhJWbQ2i7k20tDM","rect":[0,0,509,254],"offset":[0,0],"originalSize":[509,254],"capInsets":[0,0,0,0]}},{"__type__":"cc.SpriteFrame","content":{"name":"shapetractor_bush","texture":"c3gUMbcDlFX7wcbf9xlh/7","rect":[0,0,555,142],"offset":[0,0],"originalSize":[555,142],"capInsets":[0,0,0,0]}}]